setup.py
inqry/__init__.py
inqry/__main__.py
inqry/asset_qrcode.py
inqry/barcode.py
inqry/form_instructions.py
inqry/gui.py
inqry.egg-info/PKG-INFO
inqry.egg-info/SOURCES.txt
inqry.egg-info/dependency_links.txt
inqry.egg-info/requires.txt
inqry.egg-info/top_level.txt
inqry/system_specs/__init__.py
inqry/system_specs/cfgutil.py
inqry/system_specs/diskutil.py
inqry/system_specs/ios_system_profiler.py
inqry/system_specs/mac_system_profiler.py
inqry/system_specs/macdisk.py
inqry/system_specs/systemspecs.py
inqry/system_specs/win_physical_disk.py
inqry/system_specs/windisk.py
inqry/system_specs/windows_system_profiler.py