Metadata-Version: 1.1
Name: inqry
Version: 1.3.2
Summary: A cross-platform utility used to generate a QR code containing hardware specs
Home-page: https://github.com/Microsoft/InQRy
Author: ['Microsoft Apex Lab']
Author-email: apxlab@microsoft.com
License: MIT
Platform: UNKNOWN
Classifier: License :: OSI Approved :: MIT License
Classifier: Natural Language :: English
Classifier: Intended Audience :: Information Technology
Classifier: Intended Audience :: System Administrators
Classifier: Operating System :: OS Independent
Classifier: Programming Language :: Python :: 3.4
Classifier: Programming Language :: Python :: 3.5
Classifier: Programming Language :: Python :: 3.6
Classifier: Programming Language :: Python :: 3 :: Only
